<bpy>
  <Theme>
    <user_interface>
      <ThemeUserInterface
        menu_shadow_fac="0.4"
        menu_shadow_width="5"
        icon_alpha="1"
        icon_saturation="1"
        widget_emboss="#00000000"
        editor_outline="#4c4f69"
        widget_text_cursor="#7287fd"
        panel_roundness="0.8"
        transparent_checker_primary="#ccd0da"
        transparent_checker_secondary="#bcc0cc"
        transparent_checker_size="8"
        axis_x="#d20f39"
        axis_y="#40a02b"
        axis_z="#7287fd"
        gizmo_hi="#ffffff"
        gizmo_primary="#df8e1d"
        gizmo_secondary="#04a5e5"
        gizmo_view_align="#9ca0b0"
        gizmo_a="#e64553"
        gizmo_b="#179299"
        icon_scene="#4c4f69ff"
        icon_collection="#4c4f69ff"
        icon_object="#fe640bff"
        icon_object_data="#40a02bff"
        icon_modifier="#7287fdff"
        icon_shading="#e64553ff"
        icon_folder="#df8e1dff"
        icon_border_intensity="0"
        >
        <wcol_regular>
          <ThemeWidgetColors
            outline="#bcc0cc"
            inner="#bcc0ccff"
            inner_sel="#7287fdff"
            item="#4c4f69ff"
            text="#4c4f69"
            text_sel="#4c4f69"
            show_shaded="FALSE"
            shadetop="0"
            shadedown="0"
            roundness="0.8"
            >
          </ThemeWidgetColors>
        </wcol_regular>
        <wcol_tool>
          <ThemeWidgetColors
            outline="#bcc0cc"
            inner="#bcc0ccff"
            inner_sel="#7287fdff"
            item="#4c4f69ff"
            text="#4c4f69"
            text_sel="#4c4f69"
            show_shaded="FALSE"
            shadetop="0"
            shadedown="0"
            roundness="0.8"
            >
          </ThemeWidgetColors>
        </wcol_tool>
        <wcol_toolbar_item>
          <ThemeWidgetColors
            outline="#bcc0cc"
            inner="#bcc0ccff"
            inner_sel="#7287fdff"
            item="#4c4f69ff"
            text="#4c4f69"
            text_sel="#4c4f69"
            show_shaded="FALSE"
            shadetop="0"
            shadedown="0"
            roundness="0.8"
            >
          </ThemeWidgetColors>
        </wcol_toolbar_item>
        <wcol_radio>
          <ThemeWidgetColors
            outline="#bcc0cc"
            inner="#bcc0ccff"
            inner_sel="#7287fdff"
            item="#4c4f69ff"
            text="#4c4f69"
            text_sel="#4c4f69"
            show_shaded="FALSE"
            shadetop="0"
            shadedown="0"
            roundness="0.8"
            >
          </ThemeWidgetColors>
        </wcol_radio>
        <wcol_text>
          <ThemeWidgetColors
            outline="#bcc0cc"
            inner="#bcc0ccff"
            inner_sel="#bcc0ccff"
            item="#7287fdff"
            text="#4c4f69"
            text_sel="#4c4f69"
            show_shaded="FALSE"
            shadetop="0"
            shadedown="0"
            roundness="0.8"
            >
          </ThemeWidgetColors>
        </wcol_text>
        <wcol_option>
          <ThemeWidgetColors
            outline="#bcc0cc"
            inner="#bcc0ccff"
            inner_sel="#7287fdff"
            item="#4c4f69ff"
            text="#4c4f69"
            text_sel="#4c4f69"
            show_shaded="FALSE"
            shadetop="0"
            shadedown="0"
            roundness="1"
            >
          </ThemeWidgetColors>
        </wcol_option>
        <wcol_toggle>
          <ThemeWidgetColors
            outline="#bcc0cc"
            inner="#bcc0ccff"
            inner_sel="#7287fdff"
            item="#4c4f69ff"
            text="#4c4f69"
            text_sel="#4c4f69"
            show_shaded="FALSE"
            shadetop="0"
            shadedown="0"
            roundness="0.8"
            >
          </ThemeWidgetColors>
        </wcol_toggle>
        <wcol_num>
          <ThemeWidgetColors
            outline="#bcc0cc"
            inner="#bcc0ccff"
            inner_sel="#ccd0daff"
            item="#7287fdff"
            text="#4c4f69"
            text_sel="#4c4f69"
            show_shaded="FALSE"
            shadetop="0"
            shadedown="0"
            roundness="0.8"
            >
          </ThemeWidgetColors>
        </wcol_num>
        <wcol_numslider>
          <ThemeWidgetColors
            outline="#bcc0cc"
            inner="#bcc0ccff"
            inner_sel="#bcc0ccff"
            item="#7287fdff"
            text="#4c4f69"
            text_sel="#4c4f69"
            show_shaded="FALSE"
            shadetop="0"
            shadedown="0"
            roundness="0.8"
            >
          </ThemeWidgetColors>
        </wcol_numslider>
        <wcol_box>
          <ThemeWidgetColors
            outline="#7c7f93"
            inner="#ccd0daff"
            inner_sel="#7287fdff"
            item="#4c4f69ff"
            text="#4c4f69"
            text_sel="#4c4f69"
            show_shaded="TRUE"
            shadetop="0"
            shadedown="0"
            roundness="0.8"
            >
          </ThemeWidgetColors>
        </wcol_box>
        <wcol_menu>
          <ThemeWidgetColors
            outline="#bcc0cc"
            inner="#bcc0ccff"
            inner_sel="#7287fdff"
            item="#4c4f69ff"
            text="#4c4f69"
            text_sel="#4c4f69"
            show_shaded="FALSE"
            shadetop="0"
            shadedown="0"
            roundness="0.8"
            >
          </ThemeWidgetColors>
        </wcol_menu>
        <wcol_pulldown>
          <ThemeWidgetColors
            outline="#bcc0cc"
            inner="#bcc0ccff"
            inner_sel="#7287fdff"
            item="#4c4f69ff"
            text="#4c4f69"
            text_sel="#4c4f69"
            show_shaded="FALSE"
            shadetop="0"
            shadedown="0"
            roundness="0.8"
            >
          </ThemeWidgetColors>
        </wcol_pulldown>
        <wcol_menu_back>
          <ThemeWidgetColors
            outline="#7c7f93"
            inner="#ccd0daff"
            inner_sel="#7287fdff"
            item="#4c4f69ff"
            text="#4c4f69"
            text_sel="#4c4f69"
            show_shaded="FALSE"
            shadetop="0"
            shadedown="0"
            roundness="1"
            >
          </ThemeWidgetColors>
        </wcol_menu_back>
        <wcol_pie_menu>
          <ThemeWidgetColors
            outline="#bcc0cc"
            inner="#bcc0ccff"
            inner_sel="#7287fdff"
            item="#39437eff"
            text="#4c4f69"
            text_sel="#4c4f69"
            show_shaded="FALSE"
            shadetop="0"
            shadedown="0"
            roundness="0.8"
            >
          </ThemeWidgetColors>
        </wcol_pie_menu>
        <wcol_tooltip>
          <ThemeWidgetColors
            outline="#4c4f69"
            inner="#4c4f69ff"
            inner_sel="#7287fdff"
            item="#eff1f5ff"
            text="#eff1f5"
            text_sel="#eff1f5"
            show_shaded="FALSE"
            shadetop="0"
            shadedown="0"
            roundness="0.8"
            >
          </ThemeWidgetColors>
        </wcol_tooltip>
        <wcol_menu_item>
          <ThemeWidgetColors
            outline="#ccd0da"
            inner="#ccd0daff"
            inner_sel="#7287fdff"
            item="#4c4f69ff"
            text="#4c4f69"
            text_sel="#4c4f69"
            show_shaded="FALSE"
            shadetop="0"
            shadedown="0"
            roundness="0.8"
            >
          </ThemeWidgetColors>
        </wcol_menu_item>
        <wcol_scroll>
          <ThemeWidgetColors
            outline="#bcc0cc"
            inner="#bcc0ccff"
            inner_sel="#bcc0ccff"
            item="#7c7f93ff"
            text="#4c4f69"
            text_sel="#4c4f69"
            show_shaded="FALSE"
            shadetop="0"
            shadedown="0"
            roundness="1"
            >
          </ThemeWidgetColors>
        </wcol_scroll>
        <wcol_progress>
          <ThemeWidgetColors
            outline="#bcc0cc"
            inner="#bcc0ccff"
            inner_sel="#7287fdff"
            item="#7287fdff"
            text="#4c4f69"
            text_sel="#4c4f69"
            show_shaded="FALSE"
            shadetop="0"
            shadedown="0"
            roundness="0.8"
            >
          </ThemeWidgetColors>
        </wcol_progress>
        <wcol_list_item>
          <ThemeWidgetColors
            outline="#ccd0da"
            inner="#ccd0daff"
            inner_sel="#dce0e8ff"
            item="#7287fdff"
            text="#4c4f69"
            text_sel="#4c4f69"
            show_shaded="FALSE"
            shadetop="0"
            shadedown="0"
            roundness="0.8"
            >
          </ThemeWidgetColors>
        </wcol_list_item>
        <wcol_view_item>
          <ThemeWidgetColors
            outline="#bcc0cc"
            inner="#bcc0ccff"
            inner_sel="#7287fdff"
            item="#acb0beff"
            text="#4c4f69"
            text_sel="#4c4f69"
            show_shaded="FALSE"
            shadetop="0"
            shadedown="0"
            roundness="0.8"
            >
          </ThemeWidgetColors>
        </wcol_view_item>
        <wcol_state>
          <ThemeWidgetStateColors
            inner_anim="#519542"
            inner_anim_sel="#40a02b"
            inner_key="#c97f19"
            inner_key_sel="#df8e1d"
            inner_driven="#7746b7"
            inner_driven_sel="#8839ef"
            inner_overridden="#51bac0"
            inner_overridden_sel="#179299"
            inner_changed="#c8510c"
            inner_changed_sel="#fe640b"
            blend="0.5"
            >
          </ThemeWidgetStateColors>
        </wcol_state>
        <wcol_tab>
          <ThemeWidgetColors
            outline="#acb0be"
            inner="#acb0beff"
            inner_sel="#dce0e8ff"
            item="#4c4f69ff"
            text="#4c4f69"
            text_sel="#4c4f69"
            show_shaded="FALSE"
            shadetop="0"
            shadedown="0"
            roundness="0.8"
            >
          </ThemeWidgetColors>
        </wcol_tab>
      </ThemeUserInterface>
    </user_interface>
    <view_3d>
      <ThemeView3D
        grid="#4c4f6980"
        clipping_border_3d="#3f3f3fff"
        wire="#000000"
        wire_edit="#000000"
        edge_width="1"
        gp_vertex="#000000"
        gp_vertex_select="#7287fd"
        gp_vertex_size="3"
        text_grease_pencil="#b5e61d"
        object_selected="#39437e"
        object_active="#7287fd"
        text_keyframe="#ddd700"
        camera="#000000"
        empty="#000000"
        light="#00000050"
        speaker="#000000"
        vertex="#000000"
        vertex_select="#7287fd"
        vertex_active="#000000"
        vertex_size="3"
        vertex_bevel="#00a5ff"
        vertex_unreferenced="#000000"
        edge_select="#7287fd"
        edge_seam="#db2512"
        edge_sharp="#00ffff"
        edge_crease="#cc0099"
        edge_bevel="#00a5ff"
        edge_facesel="#4b4b4b"
        freestyle_edge_mark="#7fff7f"
        face="#ffffff02"
        face_select="#7287fd2e"
        face_dot="#7287fd"
        facedot_size="3"
        freestyle_face_mark="#7fff7f4d"
        face_retopology="#50c8ff0f"
        face_back="#ff0000b3"
        face_front="#0000ffb3"
        nurb_uline="#909000"
        nurb_vline="#803060"
        nurb_sel_uline="#f0ff40"
        nurb_sel_vline="#f090a0"
        act_spline="#db2512"
        handle_free="#000000"
        handle_auto="#909000"
        handle_vect="#409030"
        handle_sel_vect="#40c030"
        handle_align="#803060"
        handle_sel_free="#000000"
        handle_sel_auto="#f0ff40"
        handle_sel_align="#f090a0"
        lastsel_point="#ffffff"
        extra_edge_len="#150806"
        extra_edge_angle="#4d4d00"
        extra_face_angle="#0000cc"
        extra_face_area="#004d00"
        editmesh_active="#ffffff33"
        normal="#22dddd"
        vertex_normal="#2361dd"
        split_normal="#dd23dd"
        bone_pose="#50c8ff"
        bone_pose_active="#8cffff"
        bone_solid="#b2b2b2"
        bone_locked_weight="#ff000080"
        bundle_solid="#c8c8c8"
        camera_path="#000000"
        camera_passepartout="#000000"
        skin_root="#b44d4d"
        view_overlay="#000000"
        transform="#ffffff"
        frame_current="#4772b3"
        paint_curve_handle="#7fff7f7f"
        paint_curve_pivot="#ff7f7f7f"
        outline_width="1"
        object_origin_size="6"
        >
        <space>
          <ThemeSpaceGradient
            title="#4c4f69"
            text="#4c4f69"
            text_hi="#4c4f69"
            header="#dce0e800"
            header_text="#4c4f69"
            header_text_hi="#4c4f69"
            button="#dce0e800"
            button_title="#4c4f69"
            button_text="#4c4f69"
            button_text_hi="#4c4f69"
            navigation_bar="#dce0e8ff"
            execution_buts="#dce0e8ff"
            tab_active="#9ca0b0"
            tab_inactive="#bcc0cc"
            tab_back="#dce0e8ff"
            tab_outline="#dce0e8"
            >
            <gradients>
              <ThemeGradientColors
                background_type="RADIAL"
                high_gradient="#e6e9ef"
                gradient="#ccd0da"
                >
              </ThemeGradientColors>
            </gradients>
            <panelcolors>
              <ThemePanelColors
                header="#ccd0daff"
                back="#ccd0daff"
                sub_back="#ccd0daff"
                >
              </ThemePanelColors>
            </panelcolors>
          </ThemeSpaceGradient>
        </space>
      </ThemeView3D>
    </view_3d>
    <graph_editor>
      <ThemeGraphEditor
        grid="#4c4f69"
        frame_current="#7287fd"
        time_scrub_background="#dce0e8ff"
        time_marker_line="#4c4f69ff"
        time_marker_line_selected="#7287fdff"
        window_sliders="#969696"
        channels_region="#bcc0cc"
        dopesheet_channel="#bcc0cc"
        dopesheet_subchannel="#bcc0cc"
        channel_group="#bcc0cc"
        active_channels_group="#bcc0cc"
        preview_range="#a14d0066"
        vertex="#000000"
        vertex_select="#39437e"
        vertex_active="#7287fd"
        vertex_size="6"
        vertex_bevel="#000000"
        vertex_unreferenced="#000000"
        handle_free="#000000"
        handle_auto="#909000"
        handle_vect="#409030"
        handle_sel_vect="#40c030"
        handle_align="#803060"
        handle_sel_free="#000000"
        handle_sel_auto="#f0ff40"
        handle_sel_align="#f090a0"
        handle_auto_clamped="#994030"
        handle_sel_auto_clamped="#f0af90"
        lastsel_point="#ffffff"
        handle_vertex="#000000"
        handle_vertex_select="#7287fd"
        handle_vertex_size="5"
        >
        <space>
          <ThemeSpaceGeneric
            back="#dce0e8"
            title="#4c4f69"
            text="#4c4f69"
            text_hi="#4c4f69"
            header="#dce0e8ff"
            header_text="#4c4f69"
            header_text_hi="#4c4f69"
            button="#dce0e8ff"
            button_title="#4c4f69"
            button_text="#4c4f69"
            button_text_hi="#4c4f69"
            navigation_bar="#dce0e8ff"
            execution_buts="#dce0e8ff"
            tab_active="#9ca0b0"
            tab_inactive="#bcc0cc"
            tab_back="#dce0e8ff"
            tab_outline="#dce0e8"
            >
            <panelcolors>
              <ThemePanelColors
                header="#ccd0daff"
                back="#ccd0daff"
                sub_back="#ccd0daff"
                >
              </ThemePanelColors>
            </panelcolors>
          </ThemeSpaceGeneric>
        </space>
        <space_list>
          <ThemeSpaceListGeneric
            list="#dce0e8"
            list_title="#4c4f69"
            list_text="#4c4f69"
            list_text_hi="#7287fd"
            >
          </ThemeSpaceListGeneric>
        </space_list>
      </ThemeGraphEditor>
    </graph_editor>
    <file_browser>
      <ThemeFileBrowser
        selected_file="#7287fd"
        row_alternate="#ccd0da45"
        >
        <space>
          <ThemeSpaceGeneric
            back="#dce0e8"
            title="#4c4f69"
            text="#4c4f69"
            text_hi="#4c4f69"
            header="#dce0e8ff"
            header_text="#4c4f69"
            header_text_hi="#4c4f69"
            button="#dce0e8ff"
            button_title="#4c4f69"
            button_text="#4c4f69"
            button_text_hi="#4c4f69"
            navigation_bar="#dce0e8ff"
            execution_buts="#dce0e8ff"
            tab_active="#9ca0b0"
            tab_inactive="#bcc0cc"
            tab_back="#dce0e8ff"
            tab_outline="#dce0e8"
            >
            <panelcolors>
              <ThemePanelColors
                header="#ccd0daff"
                back="#ccd0daff"
                sub_back="#ccd0daff"
                >
              </ThemePanelColors>
            </panelcolors>
          </ThemeSpaceGeneric>
        </space>
      </ThemeFileBrowser>
    </file_browser>
    <nla_editor>
      <ThemeNLAEditor
        grid="#4c4f69"
        view_sliders="#969696"
        dopesheet_channel="#bcc0cc"
        nla_track="#bcc0cc"
        active_action="#bcc0cc66"
        active_action_unset="#bcc0cc4d"
        preview_range="#a14d0066"
        strips="#0d0d0d"
        strips_selected="#7287fd"
        transition_strips="#1c2630"
        transition_strips_selected="#2e75db"
        meta_strips="#332642"
        meta_strips_selected="#692196"
        sound_strips="#2b3d3d"
        sound_strips_selected="#1f7a7a"
        tweak="#4df31a"
        tweak_duplicate="#d90000"
        keyframe_border="#000000ff"
        keyframe_border_selected="#000000ff"
        frame_current="#7287fd"
        time_scrub_background="#dce0e8ff"
        time_marker_line="#ffffff4d"
        time_marker_line_selected="#ffffffb3"
        >
        <space>
          <ThemeSpaceGeneric
            back="#dce0e8"
            title="#4c4f69"
            text="#4c4f69"
            text_hi="#4c4f69"
            header="#dce0e8ff"
            header_text="#4c4f69"
            header_text_hi="#4c4f69"
            button="#dce0e8ff"
            button_title="#4c4f69"
            button_text="#4c4f69"
            button_text_hi="#4c4f69"
            navigation_bar="#dce0e8ff"
            execution_buts="#dce0e8ff"
            tab_active="#9ca0b0"
            tab_inactive="#bcc0cc"
            tab_back="#dce0e8ff"
            tab_outline="#dce0e8"
            >
            <panelcolors>
              <ThemePanelColors
                header="#ccd0daff"
                back="#ccd0daff"
                sub_back="#ccd0daff"
                >
              </ThemePanelColors>
            </panelcolors>
          </ThemeSpaceGeneric>
        </space>
        <space_list>
          <ThemeSpaceListGeneric
            list="#dce0e8"
            list_title="#4c4f69"
            list_text="#4c4f69"
            list_text_hi="#7287fd"
            >
          </ThemeSpaceListGeneric>
        </space_list>
      </ThemeNLAEditor>
    </nla_editor>
    <dopesheet_editor>
      <ThemeDopeSheet
        grid="#4c4f69"
        frame_current="#7287fd"
        time_scrub_background="#dce0e8ff"
        time_marker_line="#4c4f69ff"
        time_marker_line_selected="#7287fdff"
        value_sliders="#000000"
        view_sliders="#c0c0c0"
        dopesheet_channel="#bcc0cc66"
        dopesheet_subchannel="#bcc0cc66"
        channels="#bcc0cc66"
        channels_selected="#bcc0cc66"
        channel_group="#bcc0cc66"
        active_channels_group="#bcc0cc67"
        long_key="#ffffff1f"
        long_key_selected="#7287fd99"
        keyframe="#bfbfbf"
        keyframe_selected="#7287fd"
        keyframe_extreme="#e8b3cc"
        keyframe_extreme_selected="#f28080"
        keyframe_breakdown="#b3dbe8"
        keyframe_breakdown_selected="#54bfed"
        keyframe_jitter="#94e575"
        keyframe_jitter_selected="#61c042"
        keyframe_movehold="#808080"
        keyframe_movehold_selected="#7287fd"
        keyframe_border="#000000ff"
        keyframe_border_selected="#000000ff"
        keyframe_scale_factor="1"
        summary="#4d272766"
        preview_range="#a14d0066"
        interpolation_line="#94e575cc"
        simulated_frames="#8839efff"
        >
        <space>
          <ThemeSpaceGeneric
            back="#dce0e8"
            title="#4c4f69"
            text="#4c4f69"
            text_hi="#4c4f69"
            header="#dce0e8ff"
            header_text="#4c4f69"
            header_text_hi="#4c4f69"
            button="#dce0e8ff"
            button_title="#4c4f69"
            button_text="#4c4f69"
            button_text_hi="#4c4f69"
            navigation_bar="#dce0e8ff"
            execution_buts="#dce0e8ff"
            tab_active="#9ca0b0"
            tab_inactive="#bcc0cc"
            tab_back="#dce0e8ff"
            tab_outline="#dce0e8"
            >
            <panelcolors>
              <ThemePanelColors
                header="#ccd0daff"
                back="#ccd0daff"
                sub_back="#ccd0daff"
                >
              </ThemePanelColors>
            </panelcolors>
          </ThemeSpaceGeneric>
        </space>
        <space_list>
          <ThemeSpaceListGeneric
            list="#dce0e8"
            list_title="#4c4f69"
            list_text="#4c4f69"
            list_text_hi="#7287fd"
            >
          </ThemeSpaceListGeneric>
        </space_list>
      </ThemeDopeSheet>
    </dopesheet_editor>
    <image_editor>
      <ThemeImageEditor
        grid="#8c8fa1ff"
        vertex="#000000"
        vertex_select="#7287fd"
        vertex_active="#000000"
        vertex_size="3"
        vertex_bevel="#000000"
        vertex_unreferenced="#000000"
        face="#ffffff0a"
        face_select="#7287fd3c"
        face_dot="#7287fd"
        facedot_size="3"
        freestyle_face_mark="#7fff7f33"
        face_retopology="#00000000"
        face_back="#00000000"
        face_front="#00000000"
        editmesh_active="#ffffff40"
        wire_edit="#c0c0c0"
        edge_width="1"
        edge_select="#7287fd"
        scope_back="#727272ff"
        preview_stitch_face="#7f7f0033"
        preview_stitch_edge="#ff00ff33"
        preview_stitch_vert="#0000ff33"
        preview_stitch_stitchable="#00ff00ff"
        preview_stitch_unstitchable="#ff0000ff"
        preview_stitch_active="#e1d2c323"
        uv_shadow="#707070ff"
        frame_current="#4772b3"
        metadatabg="#000000"
        metadatatext="#ffffff"
        handle_free="#000000"
        handle_auto="#909000"
        handle_align="#803060"
        handle_sel_free="#000000"
        handle_sel_auto="#f0ff40"
        handle_sel_align="#f090a0"
        handle_auto_clamped="#000000"
        handle_sel_auto_clamped="#000000"
        handle_vertex="#000000"
        handle_vertex_select="#ffff00"
        handle_vertex_size="5"
        paint_curve_handle="#7fff7f7f"
        paint_curve_pivot="#ff7f7f7f"
        >
        <space>
          <ThemeSpaceGeneric
            back="#dce0e8"
            title="#4c4f69"
            text="#4c4f69"
            text_hi="#4c4f69"
            header="#dce0e8ff"
            header_text="#4c4f69"
            header_text_hi="#4c4f69"
            button="#dce0e800"
            button_title="#4c4f69"
            button_text="#4c4f69"
            button_text_hi="#4c4f69"
            navigation_bar="#dce0e8ff"
            execution_buts="#dce0e8ff"
            tab_active="#9ca0b0"
            tab_inactive="#bcc0cc"
            tab_back="#dce0e8ff"
            tab_outline="#dce0e8"
            >
            <panelcolors>
              <ThemePanelColors
                header="#ccd0daff"
                back="#ccd0daff"
                sub_back="#ccd0daff"
                >
              </ThemePanelColors>
            </panelcolors>
          </ThemeSpaceGeneric>
        </space>
      </ThemeImageEditor>
    </image_editor>
    <sequence_editor>
      <ThemeSequenceEditor
        grid="#4c4f69"
        window_sliders="#a0a0a0"
        movie_strip="#7287fd"
        movieclip_strip="#e64553"
        image_strip="#fe640b"
        scene_strip="#df8e1d"
        audio_strip="#209fb5"
        effect_strip="#ea76cb"
        color_strip="#8c8fa1"
        meta_strip="#39437e"
        mask_strip="#dd7878"
        text_strip="#4c4f69"
        active_strip="#7287fd"
        selected_strip="#39437e"
        frame_current="#7287fd"
        time_scrub_background="#dce0e8ff"
        time_marker_line="#4c4f69ff"
        time_marker_line_selected="#7287fdff"
        keyframe="#7287fd"
        draw_action="#50c8ff"
        preview_back="#000000"
        metadatabg="#000000"
        metadatatext="#ffffff"
        preview_range="#a14d0066"
        row_alternate="#8c8fa123"
        >
        <space>
          <ThemeSpaceGeneric
            back="#dce0e8"
            title="#4c4f69"
            text="#4c4f69"
            text_hi="#4c4f69"
            header="#dce0e8ff"
            header_text="#4c4f69"
            header_text_hi="#4c4f69"
            button="#dce0e8ff"
            button_title="#4c4f69"
            button_text="#4c4f69"
            button_text_hi="#4c4f69"
            navigation_bar="#dce0e8ff"
            execution_buts="#dce0e8ff"
            tab_active="#9ca0b0"
            tab_inactive="#bcc0cc"
            tab_back="#dce0e8ff"
            tab_outline="#dce0e8"
            >
            <panelcolors>
              <ThemePanelColors
                header="#ccd0daff"
                back="#ccd0daff"
                sub_back="#ccd0daff"
                >
              </ThemePanelColors>
            </panelcolors>
          </ThemeSpaceGeneric>
        </space>
        <space_list>
          <ThemeSpaceListGeneric
            list="#dce0e8"
            list_title="#4c4f69"
            list_text="#4c4f69"
            list_text_hi="#7287fd"
            >
          </ThemeSpaceListGeneric>
        </space_list>
      </ThemeSequenceEditor>
    </sequence_editor>
    <properties>
      <ThemeProperties
        match="#7287fd"
        active_modifier="#7287fdff"
        >
        <space>
          <ThemeSpaceGeneric
            back="#dce0e8"
            title="#4c4f69"
            text="#4c4f69"
            text_hi="#4c4f69"
            header="#dce0e8ff"
            header_text="#4c4f69"
            header_text_hi="#4c4f69"
            button="#dce0e8ff"
            button_title="#4c4f69"
            button_text="#4c4f69"
            button_text_hi="#4c4f69"
            navigation_bar="#acb0beff"
            execution_buts="#dce0e8ff"
            tab_active="#9ca0b0"
            tab_inactive="#bcc0cc"
            tab_back="#dce0e8ff"
            tab_outline="#dce0e8"
            >
            <panelcolors>
              <ThemePanelColors
                header="#ccd0daff"
                back="#ccd0daff"
                sub_back="#ccd0daff"
                >
              </ThemePanelColors>
            </panelcolors>
          </ThemeSpaceGeneric>
        </space>
      </ThemeProperties>
    </properties>
    <text_editor>
      <ThemeTextEditor
        line_numbers="#4c4f69"
        line_numbers_background="#bcc0cc"
        selected_text="#2d4366"
        cursor="#ff0000"
        syntax_builtin="#d20f39"
        syntax_symbols="#dd7878"
        syntax_special="#40a02b"
        syntax_preprocessor="#8839ef"
        syntax_reserved="#fe640b"
        syntax_comment="#8c8fa1"
        syntax_string="#df8e1d"
        syntax_numbers="#7287fd"
        >
        <space>
          <ThemeSpaceGeneric
            back="#dce0e8"
            title="#4c4f69"
            text="#4c4f69"
            text_hi="#4c4f69"
            header="#dce0e8ff"
            header_text="#4c4f69"
            header_text_hi="#4c4f69"
            button="#dce0e8ff"
            button_title="#4c4f69"
            button_text="#4c4f69"
            button_text_hi="#4c4f69"
            navigation_bar="#dce0e8ff"
            execution_buts="#dce0e8ff"
            tab_active="#9ca0b0"
            tab_inactive="#bcc0cc"
            tab_back="#dce0e8ff"
            tab_outline="#dce0e8"
            >
            <panelcolors>
              <ThemePanelColors
                header="#ccd0daff"
                back="#ccd0daff"
                sub_back="#ccd0daff"
                >
              </ThemePanelColors>
            </panelcolors>
          </ThemeSpaceGeneric>
        </space>
      </ThemeTextEditor>
    </text_editor>
    <node_editor>
      <ThemeNodeEditor
        grid="#4c4f69"
        node_selected="#39437e"
        node_active="#7287fd"
        wire="#4c4f69ff"
        wire_inner="#8d8d8d"
        wire_select="#7287fd80"
        selected_text="#4c4f69"
        node_backdrop="#dce0e8ff"
        converter_node="#7287fd"
        color_node="#df8e1d"
        group_node="#40a02b"
        group_socket_node="#4c4f69"
        frame_node="#9ca0b056"
        matte_node="#d20f39"
        distor_node="#209fb5"
        noodle_curving="5"
        grid_levels="1"
        dash_alpha="0.5"
        input_node="#e64553"
        output_node="#d20f39"
        filter_node="#8839ef"
        vector_node="#1e66f5"
        texture_node="#fe640b"
        shader_node="#40a02b"
        script_node="#209fb5"
        pattern_node="#6c696f"
        layout_node="#6c696f"
        geometry_node="#40a02b"
        attribute_node="#1e66f5"
        simulation_zone="#8839ef33"
        >
        <space>
          <ThemeSpaceGeneric
            back="#dce0e8"
            title="#4c4f69"
            text="#4c4f69"
            text_hi="#4c4f69"
            header="#dce0e8ff"
            header_text="#4c4f69"
            header_text_hi="#4c4f69"
            button="#dce0e800"
            button_title="#4c4f69"
            button_text="#4c4f69"
            button_text_hi="#4c4f69"
            navigation_bar="#dce0e8ff"
            execution_buts="#dce0e8ff"
            tab_active="#9ca0b0"
            tab_inactive="#bcc0cc"
            tab_back="#dce0e8ff"
            tab_outline="#dce0e8"
            >
            <panelcolors>
              <ThemePanelColors
                header="#ccd0daff"
                back="#ccd0daff"
                sub_back="#ccd0daff"
                >
              </ThemePanelColors>
            </panelcolors>
          </ThemeSpaceGeneric>
        </space>
        <space_list>
          <ThemeSpaceListGeneric
            list="#dce0e8"
            list_title="#4c4f69"
            list_text="#4c4f69"
            list_text_hi="#7287fd"
            >
          </ThemeSpaceListGeneric>
        </space_list>
      </ThemeNodeEditor>
    </node_editor>
    <outliner>
      <ThemeOutliner
        match="#40a02b"
        selected_highlight="#bcc0cc"
        active="#7287fd"
        selected_object="#4c4f69"
        active_object="#4c4f69"
        edited_object="#40a02b66"
        row_alternate="#ffffff04"
        >
        <space>
          <ThemeSpaceGeneric
            back="#dce0e8"
            title="#4c4f69"
            text="#4c4f69"
            text_hi="#4c4f69"
            header="#dce0e8ff"
            header_text="#4c4f69"
            header_text_hi="#4c4f69"
            button="#dce0e8ff"
            button_title="#4c4f69"
            button_text="#4c4f69"
            button_text_hi="#4c4f69"
            navigation_bar="#dce0e8ff"
            execution_buts="#dce0e8ff"
            tab_active="#9ca0b0"
            tab_inactive="#bcc0cc"
            tab_back="#dce0e8ff"
            tab_outline="#dce0e8"
            >
            <panelcolors>
              <ThemePanelColors
                header="#ccd0daff"
                back="#ccd0daff"
                sub_back="#ccd0daff"
                >
              </ThemePanelColors>
            </panelcolors>
          </ThemeSpaceGeneric>
        </space>
      </ThemeOutliner>
    </outliner>
    <info>
      <ThemeInfo
        info_selected="#7287fd"
        info_selected_text="#dce0e8"
        info_error="#e64553ff"
        info_error_text="#dce0e8"
        info_warning="#df8e1dff"
        info_warning_text="#dce0e8"
        info_info="#1e66f5ff"
        info_info_text="#dce0e8"
        info_debug="#8839efff"
        info_debug_text="#dce0e8"
        info_property="#40a02bff"
        info_property_text="#dce0e8"
        info_operator="#179299ff"
        info_operator_text="#dce0e8"
        >
        <space>
          <ThemeSpaceGeneric
            back="#dce0e8"
            title="#4c4f69"
            text="#4c4f69"
            text_hi="#4c4f69"
            header="#dce0e8ff"
            header_text="#4c4f69"
            header_text_hi="#4c4f69"
            button="#dce0e8ff"
            button_title="#4c4f69"
            button_text="#4c4f69"
            button_text_hi="#4c4f69"
            navigation_bar="#dce0e8ff"
            execution_buts="#dce0e8ff"
            tab_active="#9ca0b0"
            tab_inactive="#bcc0cc"
            tab_back="#dce0e8ff"
            tab_outline="#dce0e8"
            >
            <panelcolors>
              <ThemePanelColors
                header="#ccd0daff"
                back="#ccd0daff"
                sub_back="#ccd0daff"
                >
              </ThemePanelColors>
            </panelcolors>
          </ThemeSpaceGeneric>
        </space>
      </ThemeInfo>
    </info>
    <preferences>
      <ThemePreferences>
        <space>
          <ThemeSpaceGeneric
            back="#dce0e8"
            title="#4c4f69"
            text="#4c4f69"
            text_hi="#4c4f69"
            header="#dce0e8ff"
            header_text="#4c4f69"
            header_text_hi="#4c4f69"
            button="#dce0e8ff"
            button_title="#4c4f69"
            button_text="#4c4f69"
            button_text_hi="#4c4f69"
            navigation_bar="#dce0e8ff"
            execution_buts="#dce0e8ff"
            tab_active="#9ca0b0"
            tab_inactive="#bcc0cc"
            tab_back="#dce0e8ff"
            tab_outline="#dce0e8"
            >
            <panelcolors>
              <ThemePanelColors
                header="#ccd0daff"
                back="#ccd0daff"
                sub_back="#ccd0daff"
                >
              </ThemePanelColors>
            </panelcolors>
          </ThemeSpaceGeneric>
        </space>
      </ThemePreferences>
    </preferences>
    <console>
      <ThemeConsole
        line_output="#7287fd"
        line_input="#4c4f69"
        line_info="#40a02b"
        line_error="#e64553"
        cursor="#8839ef"
        select="#bcc0ccff"
        >
        <space>
          <ThemeSpaceGeneric
            back="#dce0e8"
            title="#4c4f69"
            text="#4c4f69"
            text_hi="#4c4f69"
            header="#dce0e8ff"
            header_text="#4c4f69"
            header_text_hi="#4c4f69"
            button="#dce0e8ff"
            button_title="#4c4f69"
            button_text="#4c4f69"
            button_text_hi="#4c4f69"
            navigation_bar="#dce0e8ff"
            execution_buts="#dce0e8ff"
            tab_active="#9ca0b0"
            tab_inactive="#bcc0cc"
            tab_back="#dce0e8ff"
            tab_outline="#dce0e8"
            >
            <panelcolors>
              <ThemePanelColors
                header="#ccd0daff"
                back="#ccd0daff"
                sub_back="#ccd0daff"
                >
              </ThemePanelColors>
            </panelcolors>
          </ThemeSpaceGeneric>
        </space>
      </ThemeConsole>
    </console>
    <clip_editor>
      <ThemeClipEditor
        grid="#4c4f69ff"
        marker_outline="#000000"
        marker="#808000"
        active_marker="#ffffff"
        selected_marker="#ffff00"
        disabled_marker="#7f0000"
        locked_marker="#7f7f7f"
        path_before="#ff0000"
        path_after="#0000ff"
        path_keyframe_before="#ffc4c4"
        path_keyframe_after="#c4c4ff"
        frame_current="#4772b3"
        time_scrub_background="#181818ff"
        time_marker_line="#ffffff4d"
        time_marker_line_selected="#ffffffb3"
        strips="#ffffff"
        strips_selected="#7287fd"
        metadatabg="#000000"
        metadatatext="#ffffff"
        handle_free="#000000"
        handle_auto="#909000"
        handle_align="#803060"
        handle_sel_free="#000000"
        handle_sel_auto="#f0ff40"
        handle_sel_align="#f090a0"
        handle_auto_clamped="#994030"
        handle_sel_auto_clamped="#f0af90"
        handle_vertex="#000000"
        handle_vertex_select="#7287fd"
        handle_vertex_size="5"
        >
        <space>
          <ThemeSpaceGeneric
            back="#dce0e8"
            title="#4c4f69"
            text="#4c4f69"
            text_hi="#4c4f69"
            header="#dce0e8ff"
            header_text="#4c4f69"
            header_text_hi="#4c4f69"
            button="#dce0e800"
            button_title="#4c4f69"
            button_text="#4c4f69"
            button_text_hi="#4c4f69"
            navigation_bar="#dce0e8ff"
            execution_buts="#dce0e8ff"
            tab_active="#9ca0b0"
            tab_inactive="#bcc0cc"
            tab_back="#dce0e8ff"
            tab_outline="#dce0e8"
            >
            <panelcolors>
              <ThemePanelColors
                header="#ccd0daff"
                back="#ccd0daff"
                sub_back="#ccd0daff"
                >
              </ThemePanelColors>
            </panelcolors>
          </ThemeSpaceGeneric>
        </space>
        <space_list>
          <ThemeSpaceListGeneric
            list="#dce0e8"
            list_title="#4c4f69"
            list_text="#4c4f69"
            list_text_hi="#7287fd"
            >
          </ThemeSpaceListGeneric>
        </space_list>
      </ThemeClipEditor>
    </clip_editor>
    <topbar>
      <ThemeTopBar>
        <space>
          <ThemeSpaceGeneric
            back="#dce0e8"
            title="#4c4f69"
            text="#4c4f69"
            text_hi="#4c4f69"
            header="#acb0beff"
            header_text="#4c4f69"
            header_text_hi="#4c4f69"
            button="#dce0e8ff"
            button_title="#4c4f69"
            button_text="#4c4f69"
            button_text_hi="#4c4f69"
            navigation_bar="#dce0e8ff"
            execution_buts="#dce0e8ff"
            tab_active="#9ca0b0"
            tab_inactive="#bcc0cc"
            tab_back="#dce0e8ff"
            tab_outline="#dce0e8"
            >
            <panelcolors>
              <ThemePanelColors
                header="#bcc0ccff"
                back="#bcc0ccff"
                sub_back="#bcc0ccff"
                >
              </ThemePanelColors>
            </panelcolors>
          </ThemeSpaceGeneric>
        </space>
      </ThemeTopBar>
    </topbar>
    <statusbar>
      <ThemeStatusBar>
        <space>
          <ThemeSpaceGeneric
            back="#dce0e8"
            title="#4c4f69"
            text="#4c4f69"
            text_hi="#4c4f69"
            header="#dce0e8ff"
            header_text="#4c4f69"
            header_text_hi="#4c4f69"
            button="#dce0e8ff"
            button_title="#4c4f69"
            button_text="#4c4f69"
            button_text_hi="#4c4f69"
            navigation_bar="#dce0e8ff"
            execution_buts="#dce0e8ff"
            tab_active="#9ca0b0"
            tab_inactive="#bcc0cc"
            tab_back="#dce0e8ff"
            tab_outline="#dce0e8"
            >
            <panelcolors>
              <ThemePanelColors
                header="#bcc0ccff"
                back="#bcc0ccff"
                sub_back="#bcc0ccff"
                >
              </ThemePanelColors>
            </panelcolors>
          </ThemeSpaceGeneric>
        </space>
      </ThemeStatusBar>
    </statusbar>
    <spreadsheet>
      <ThemeSpreadsheet
        row_alternate="#ccd0daff"
        >
        <space>
          <ThemeSpaceGeneric
            back="#dce0e8"
            title="#4c4f69"
            text="#4c4f69"
            text_hi="#4c4f69"
            header="#dce0e8ff"
            header_text="#4c4f69"
            header_text_hi="#4c4f69"
            button="#dce0e8ff"
            button_title="#4c4f69"
            button_text="#4c4f69"
            button_text_hi="#4c4f69"
            navigation_bar="#dce0e8ff"
            execution_buts="#dce0e8ff"
            tab_active="#9ca0b0"
            tab_inactive="#bcc0cc"
            tab_back="#dce0e8ff"
            tab_outline="#dce0e8"
            >
            <panelcolors>
              <ThemePanelColors
                header="#ccd0daff"
                back="#ccd0daff"
                sub_back="#ccd0daff"
                >
              </ThemePanelColors>
            </panelcolors>
          </ThemeSpaceGeneric>
        </space>
        <space_list>
          <ThemeSpaceListGeneric
            list="#dce0e8"
            list_title="#4c4f69"
            list_text="#4c4f69"
            list_text_hi="#7287fd"
            >
          </ThemeSpaceListGeneric>
        </space_list>
      </ThemeSpreadsheet>
    </spreadsheet>
    <bone_color_sets>
      <ThemeBoneColorSet
        normal="#9a0000"
        select="#bd1111"
        active="#f70a0a"
        show_colored_constraints="FALSE"
        >
      </ThemeBoneColorSet>
      <ThemeBoneColorSet
        normal="#f74018"
        select="#f66913"
        active="#fa9900"
        show_colored_constraints="FALSE"
        >
      </ThemeBoneColorSet>
      <ThemeBoneColorSet
        normal="#1e9109"
        select="#59b70b"
        active="#83ef1d"
        show_colored_constraints="FALSE"
        >
      </ThemeBoneColorSet>
      <ThemeBoneColorSet
        normal="#0a3694"
        select="#3667df"
        active="#5ec1ef"
        show_colored_constraints="FALSE"
        >
      </ThemeBoneColorSet>
      <ThemeBoneColorSet
        normal="#a9294e"
        select="#c1416a"
        active="#f05d91"
        show_colored_constraints="FALSE"
        >
      </ThemeBoneColorSet>
      <ThemeBoneColorSet
        normal="#430c78"
        select="#543aa3"
        active="#8764d5"
        show_colored_constraints="FALSE"
        >
      </ThemeBoneColorSet>
      <ThemeBoneColorSet
        normal="#24785a"
        select="#3c9579"
        active="#6fb6ab"
        show_colored_constraints="FALSE"
        >
      </ThemeBoneColorSet>
      <ThemeBoneColorSet
        normal="#4b707c"
        select="#6a8691"
        active="#9bc2cd"
        show_colored_constraints="FALSE"
        >
      </ThemeBoneColorSet>
      <ThemeBoneColorSet
        normal="#f4c90c"
        select="#eec236"
        active="#f3ff00"
        show_colored_constraints="FALSE"
        >
      </ThemeBoneColorSet>
      <ThemeBoneColorSet
        normal="#1e2024"
        select="#484c56"
        active="#ffffff"
        show_colored_constraints="FALSE"
        >
      </ThemeBoneColorSet>
      <ThemeBoneColorSet
        normal="#6f2f6a"
        select="#9845be"
        active="#d330d6"
        show_colored_constraints="FALSE"
        >
      </ThemeBoneColorSet>
      <ThemeBoneColorSet
        normal="#6c8e22"
        select="#7fb022"
        active="#bbef5b"
        show_colored_constraints="FALSE"
        >
      </ThemeBoneColorSet>
      <ThemeBoneColorSet
        normal="#8d8d8d"
        select="#b0b0b0"
        active="#dedede"
        show_colored_constraints="FALSE"
        >
      </ThemeBoneColorSet>
      <ThemeBoneColorSet
        normal="#834326"
        select="#8b5811"
        active="#bd6a11"
        show_colored_constraints="FALSE"
        >
      </ThemeBoneColorSet>
      <ThemeBoneColorSet
        normal="#08310e"
        select="#1c430b"
        active="#34622b"
        show_colored_constraints="FALSE"
        >
      </ThemeBoneColorSet>
      <ThemeBoneColorSet
        normal="#000000"
        select="#000000"
        active="#000000"
        show_colored_constraints="FALSE"
        >
      </ThemeBoneColorSet>
      <ThemeBoneColorSet
        normal="#000000"
        select="#000000"
        active="#000000"
        show_colored_constraints="FALSE"
        >
      </ThemeBoneColorSet>
      <ThemeBoneColorSet
        normal="#000000"
        select="#000000"
        active="#000000"
        show_colored_constraints="FALSE"
        >
      </ThemeBoneColorSet>
      <ThemeBoneColorSet
        normal="#000000"
        select="#000000"
        active="#000000"
        show_colored_constraints="FALSE"
        >
      </ThemeBoneColorSet>
      <ThemeBoneColorSet
        normal="#000000"
        select="#000000"
        active="#000000"
        show_colored_constraints="FALSE"
        >
      </ThemeBoneColorSet>
    </bone_color_sets>
    <collection_color>
      <ThemeCollectionColor
        color="#d20f39"
        >
      </ThemeCollectionColor>
      <ThemeCollectionColor
        color="#fe640b"
        >
      </ThemeCollectionColor>
      <ThemeCollectionColor
        color="#df8e1d"
        >
      </ThemeCollectionColor>
      <ThemeCollectionColor
        color="#40a02b"
        >
      </ThemeCollectionColor>
      <ThemeCollectionColor
        color="#04a5e5"
        >
      </ThemeCollectionColor>
      <ThemeCollectionColor
        color="#8839ef"
        >
      </ThemeCollectionColor>
      <ThemeCollectionColor
        color="#ea76cb"
        >
      </ThemeCollectionColor>
      <ThemeCollectionColor
        color="#dc8a78"
        >
      </ThemeCollectionColor>
    </collection_color>
    <strip_color>
      <ThemeStripColor
        color="#d20f39"
        >
      </ThemeStripColor>
      <ThemeStripColor
        color="#fe640b"
        >
      </ThemeStripColor>
      <ThemeStripColor
        color="#df8e1d"
        >
      </ThemeStripColor>
      <ThemeStripColor
        color="#40a02b"
        >
      </ThemeStripColor>
      <ThemeStripColor
        color="#04a5e5"
        >
      </ThemeStripColor>
      <ThemeStripColor
        color="#8839ef"
        >
      </ThemeStripColor>
      <ThemeStripColor
        color="#ea76cb"
        >
      </ThemeStripColor>
      <ThemeStripColor
        color="#dc8a78"
        >
      </ThemeStripColor>
      <ThemeStripColor
        color="#9ca0b0"
        >
      </ThemeStripColor>
    </strip_color>
  </Theme>
  <ThemeStyle>
    <panel_title>
      <ThemeFontStyle
        points="11"
        shadow="3"
        shadow_offset_x="0"
        shadow_offset_y="-1"
        shadow_alpha="0.5"
        shadow_value="0"
        >
      </ThemeFontStyle>
    </panel_title>
    <widget_label>
      <ThemeFontStyle
        points="11"
        shadow="3"
        shadow_offset_x="0"
        shadow_offset_y="-1"
        shadow_alpha="0.5"
        shadow_value="0"
        >
      </ThemeFontStyle>
    </widget_label>
    <widget>
      <ThemeFontStyle
        points="11"
        shadow="1"
        shadow_offset_x="0"
        shadow_offset_y="-1"
        shadow_alpha="0.5"
        shadow_value="0"
        >
      </ThemeFontStyle>
    </widget>
  </ThemeStyle>
</bpy>
